FinToolsAP/Decorators.py
FinToolsAP/FactorModels.py
FinToolsAP/LaTeXBuilder.py
FinToolsAP/LocalDatabase.py
FinToolsAP/MertonModel.py
FinToolsAP/UtilityFunctions.py
FinToolsAP/WebData.py
FinToolsAP/__init__.py
FinToolsAP/_config.py
FinToolsAP/_util_funcs.py
FinToolsAP/base_files/DatabaseContents.py
FinToolsAP/base_files/ExampleCreateTable.py
FinToolsAP/base_files/ExampleExtraScript.py
FinToolsAP/download_files/ffsic_download_script.py
FinToolsAP/download_files/wrds_download_script.py
FinToolsAP/shell_files/sqlite_csv_import.sh
FinToolsAP/shell_files/sqlite_null_table.sh
FinToolsAP/shell_files/sqlite_type_infer.sh
fintoolsap-1.14.16.dist-info/METADATA
fintoolsap-1.14.16.dist-info/WHEEL
fintoolsap-1.14.16.dist-info/licenses/LICENSE
fintoolsap-1.14.16.dist-info/RECORD
