Metadata-Version: 2.4
Name: FinToolsAP
Version: 1.14.16
Summary: This package is a comprehensive Python package designed for researchers and data analysts in economics and finance. It provides streamlined tools for managing, processing, and querying large datasets using a local SQLite database, as well as convenient data manipulation utilities compatible with both pandas and polars.
Project-URL: Homepage, https://github.com/AndrewPerry-Haas/FinToolsAP
Project-URL: Bug Tracker, https://github.com/AndrewPerry-Haas/FinToolsAP/issues
Author-email: Andrew Maurice Perry <andrewpe@berkeley.edu>
License-File: LICENSE
Classifier: License :: OSI Approved :: MIT License
Classifier: Operating System :: OS Independent
Classifier: Programming Language :: Python :: 3
Requires-Python: >=3.10
Requires-Dist: bottleneck==1.3.6
Requires-Dist: build<1.0,>=0.10
Requires-Dist: connectorx<1.0,>=0.4
Requires-Dist: knockknock<0.5.0,>=0.1.0
Requires-Dist: linearmodels<7.0,>=4.36
Requires-Dist: matplotlib<4.0,>=3.5
Requires-Dist: pandas<3.0,>=1.5
Requires-Dist: pathlib<2.0,>=1.0
Requires-Dist: pdoc<16.0,>=9.0
Requires-Dist: polars<2.0,>=0.16
Requires-Dist: pyarrow<25.0,>=10.0
Requires-Dist: seaborn<1.0,>=0.12
Requires-Dist: sqlalchemy<2.5,>=1.4
Requires-Dist: statsmodels<1.0,>=0.14
Requires-Dist: tqdm<5.0,>=4.64
Requires-Dist: twine<7.0,>=4.0
Requires-Dist: wrds<4.0,>=3.2
